tess_cloud/__init__.py
tess_cloud/asteroid_pipeline.py
tess_cloud/crawler.py
tess_cloud/cutout.py
tess_cloud/data/tess-s0001-spoc-ffi-catalog.parquet
tess_cloud/data/tess-s0002-spoc-ffi-catalog.parquet
tess_cloud/data/tess-s0003-spoc-ffi-catalog.parquet
tess_cloud/data/tess-s0004-spoc-ffi-catalog.parquet
tess_cloud/data/tess-s0005-spoc-ffi-catalog.parquet
tess_cloud/data/tess-s0006-spoc-ffi-catalog.parquet
tess_cloud/data/tess-s0007-spoc-ffi-catalog.parquet
tess_cloud/data/tess-s0008-spoc-ffi-catalog.parquet
tess_cloud/data/tess-s0009-spoc-ffi-catalog.parquet
tess_cloud/data/tess-s0010-spoc-ffi-catalog.parquet
tess_cloud/data/tess-s0011-spoc-ffi-catalog.parquet
tess_cloud/data/tess-s0012-spoc-ffi-catalog.parquet
tess_cloud/data/tess-s0013-spoc-ffi-catalog.parquet
tess_cloud/data/tess-s0014-spoc-ffi-catalog.parquet
tess_cloud/data/tess-s0015-spoc-ffi-catalog.parquet
tess_cloud/data/tess-s0016-spoc-ffi-catalog.parquet
tess_cloud/data/tess-s0017-spoc-ffi-catalog.parquet
tess_cloud/data/tess-s0018-spoc-ffi-catalog.parquet
tess_cloud/data/tess-s0019-spoc-ffi-catalog.parquet
tess_cloud/data/tess-s0020-spoc-ffi-catalog.parquet
tess_cloud/data/tess-s0021-spoc-ffi-catalog.parquet
tess_cloud/data/tess-s0022-spoc-ffi-catalog.parquet
tess_cloud/data/tess-s0023-spoc-ffi-catalog.parquet
tess_cloud/data/tess-s0024-spoc-ffi-catalog.parquet
tess_cloud/data/tess-s0025-spoc-ffi-catalog.parquet
tess_cloud/data/tess-s0026-spoc-ffi-catalog.parquet
tess_cloud/data/tess-s0027-spoc-ffi-catalog.parquet
tess_cloud/data/tess-s0027-tica-ffi-catalog.parquet
tess_cloud/data/tess-s0028-spoc-ffi-catalog.parquet
tess_cloud/data/tess-s0028-tica-ffi-catalog.parquet
tess_cloud/data/tess-s0029-spoc-ffi-catalog.parquet
tess_cloud/data/tess-s0029-tica-ffi-catalog.parquet
tess_cloud/data/tess-s0030-spoc-ffi-catalog.parquet
tess_cloud/data/tess-s0030-tica-ffi-catalog.parquet
tess_cloud/data/tess-s0031-spoc-ffi-catalog.parquet
tess_cloud/data/tess-s0032-spoc-ffi-catalog.parquet
tess_cloud-0.5.0.dist-info/METADATA
tess_cloud-0.5.0.dist-info/WHEEL
tess_cloud-0.5.0.dist-info/RECORD
