Metadata-Version: 2.1
Name: tess-cloud
Version: 0.5.0
Summary: Analyze NASA TESS data in the cloud.
Home-page: https://github.com/SSDataLab/tess-cloud
License: MIT
Keywords: NASA, TESS, Astronomy
Author: Geert Barentsen
Author-email: hello@geert.io
Requires-Python: >=3.8,<4.0
Classifier: Intended Audience :: Science/Research
Classifier: License :: OSI Approved :: MIT License
Classifier: Programming Language :: Python :: 3
Classifier: Programming Language :: Python :: 3.8
Classifier: Programming Language :: Python :: 3.9
Classifier: Programming Language :: Python :: 3.10
Classifier: Programming Language :: Python :: 3.11
Classifier: Topic :: Scientific/Engineering :: Astronomy
Requires-Dist: aioboto3 (>=9.0.0)
Requires-Dist: aiohttp (>=3.7.4)
Requires-Dist: astropy (>=5.2.0,<6.0.0)
Requires-Dist: backoff (>=1.10.0)
Requires-Dist: diskcache (>=5.2.1)
Requires-Dist: lightkurve (>=2.3.0,<3.0.0)
Requires-Dist: nest-asyncio (>=1.5.1)
Requires-Dist: numpy (>=1.23.0,<2.0.0)
Requires-Dist: pyarrow (>=3.0.0)
Requires-Dist: s3fs (>=0.5.2)
Requires-Dist: tess-ephem (>=0.4,<0.5)
Requires-Dist: tess-locator (>=0.6,<0.7)
Requires-Dist: tqdm (>=4.51.0)
Project-URL: Repository, https://github.com/SSDataLab/tess-cloud
